labtasker_plugin_script_generate/__init__.py
labtasker_plugin_script_generate/main.py
labtasker_plugin_script_generate-0.1.3.dist-info/METADATA
labtasker_plugin_script_generate-0.1.3.dist-info/WHEEL
labtasker_plugin_script_generate-0.1.3.dist-info/entry_points.txt
labtasker_plugin_script_generate-0.1.3.dist-info/top_level.txt
labtasker_plugin_script_generate-0.1.3.dist-info/RECORD
